stocks_br/__init__.py
stocks_br/manage_price.py
stocks_br-0.0.16.dist-info/METADATA
stocks_br-0.0.16.dist-info/WHEEL
stocks_br-0.0.16.dist-info/RECORD
