Metadata-Version: 2.3
Name: stocks-br
Version: 0.0.16
Summary: Manage Stocks
Author: Jeferson dalarmi
Requires-Python: >=3.11,<4.0
Classifier: Programming Language :: Python :: 3
Classifier: Programming Language :: Python :: 3.11
Classifier: Programming Language :: Python :: 3.12
Classifier: Programming Language :: Python :: 3.13
Requires-Dist: yfinance (>=0.2.54,<0.3.0)
